sensortransformer/__init__.py
sensortransformer/set_network.py
sensortransformer-0.1.6.dist-info/LICENSE
sensortransformer-0.1.6.dist-info/METADATA
sensortransformer-0.1.6.dist-info/WHEEL
sensortransformer-0.1.6.dist-info/top_level.txt
sensortransformer-0.1.6.dist-info/RECORD
