Metadata-Version: 2.1
Name: sensortransformer
Version: 0.1.6
Summary: Transformer Network for Time-Series and Wearable Sensor Data
Home-page: https://github.com/aqibsaeed/Sensor-Transformer
Author: Aaqib Saeed
Author-email: aqibsaeed@protonmail.com
License: MIT
Download-URL: https://pypi.org/project/sensor_transformer/
Keywords: Transformer,Attention-Mechanism,Neural Network,Time-Series,Sensors
Platform: UNKNOWN
Requires-Dist: tensorflow (>=2.4)
Requires-Dist: einops
